[
  {
    "file": "c:\\Users\\akshi\\Desktop\\SMS-Aksh\\frontend\\src\\utils\\tracebackAPI.js",
    "historyDir": "C:\\Users\\akshi\\AppData\\Roaming\\Code\\User\\History\\-324ce085",
    "entries": [
      {
        "id": "7Vfj.js",
        "time": "2026-03-10T16:03:42.602Z"
      }
    ]
  },
  {
    "file": "c:\\Users\\akshi\\Desktop\\SMS-Aksh\\frontend\\src\\pages\\security\\VisitorEntry.jsx",
    "historyDir": "C:\\Users\\akshi\\AppData\\Roaming\\Code\\User\\History\\-3a494b07",
    "entries": [
      {
        "id": "1qkw.jsx",
        "time": "2026-03-10T15:11:21.086Z"
      },
      {
        "id": "r6Qo.jsx",
        "time": "2026-03-10T16:01:05.415Z"
      },
      {
        "id": "od8H.jsx",
        "time": "2026-03-10T16:01:36.113Z"
      }
    ]
  },
  {
    "file": "c:\\Users\\akshi\\Desktop\\SMS-Aksh\\frontend\\src\\pages\\admin\\VisitorAnalytics.jsx",
    "historyDir": "C:\\Users\\akshi\\AppData\\Roaming\\Code\\User\\History\\4c3a51b4",
    "entries": [
      {
        "id": "04Vt.jsx",
        "time": "2026-03-10T15:12:00.286Z"
      },
      {
        "id": "KH18.jsx",
        "time": "2026-03-10T16:01:05.289Z"
      }
    ]
  },
  {
    "file": "c:\\Users\\akshi\\Desktop\\SMS-Aksh\\frontend\\src\\pages\\admin\\BillManagement.jsx",
    "historyDir": "C:\\Users\\akshi\\AppData\\Roaming\\Code\\User\\History\\985ec66",
    "entries": [
      {
        "id": "Zfji.jsx",
        "time": "2026-03-10T16:30:04.878Z"
      },
      {
        "id": "tsAg.jsx",
        "time": "2026-03-10T16:30:16.312Z"
      }
    ]
  }
]